pulumi_linode/__init__.py
pulumi_linode/_inputs.py
pulumi_linode/_utilities.py
pulumi_linode/account_settings.py
pulumi_linode/consumer_image_share_group_token.py
pulumi_linode/database_access_controls.py
pulumi_linode/database_mysql.py
pulumi_linode/database_mysql_v2.py
pulumi_linode/database_postgresql.py
pulumi_linode/database_postgresql_v2.py
pulumi_linode/domain.py
pulumi_linode/domain_record.py
pulumi_linode/firewall.py
pulumi_linode/firewall_device.py
pulumi_linode/firewall_settings.py
pulumi_linode/get_account.py
pulumi_linode/get_account_availabilities.py
pulumi_linode/get_account_availability.py
pulumi_linode/get_account_login.py
pulumi_linode/get_account_logins.py
pulumi_linode/get_account_settings.py
pulumi_linode/get_child_account.py
pulumi_linode/get_child_accounts.py
pulumi_linode/get_consumer_image_share_group.py
pulumi_linode/get_consumer_image_share_group_image_shares.py
pulumi_linode/get_consumer_image_share_group_token.py
pulumi_linode/get_consumer_image_share_group_tokens.py
pulumi_linode/get_database_backups.py
pulumi_linode/get_database_engines.py
pulumi_linode/get_database_mysql.py
pulumi_linode/get_database_mysql_backups.py
pulumi_linode/get_database_mysql_config.py
pulumi_linode/get_database_mysql_v2.py
pulumi_linode/get_database_postgresql.py
pulumi_linode/get_database_postgresql_config.py
pulumi_linode/get_database_postgresql_v2.py
pulumi_linode/get_databases.py
pulumi_linode/get_domain.py
pulumi_linode/get_domain_record.py
pulumi_linode/get_domain_zonefile.py
pulumi_linode/get_domains.py
pulumi_linode/get_firewall.py
pulumi_linode/get_firewall_settings.py
pulumi_linode/get_firewall_template.py
pulumi_linode/get_firewall_templates.py
pulumi_linode/get_firewalls.py
pulumi_linode/get_image.py
pulumi_linode/get_images.py
pulumi_linode/get_instance_backups.py
pulumi_linode/get_instance_networking.py
pulumi_linode/get_instance_type.py
pulumi_linode/get_instance_types.py
pulumi_linode/get_instances.py
pulumi_linode/get_interface.py
pulumi_linode-5.6.0.dist-info/METADATA
pulumi_linode-5.6.0.dist-info/WHEEL
pulumi_linode-5.6.0.dist-info/top_level.txt
pulumi_linode-5.6.0.dist-info/RECORD
